CHANGES.txt
LICENSE.txt
README.txt
setup.cfg
setup.py
version.txt
raisin/__init__.py
raisin.page.egg-info/PKG-INFO
raisin.page.egg-info/SOURCES.txt
raisin.page.egg-info/dependency_links.txt
raisin.page.egg-info/entry_points.txt
raisin.page.egg-info/namespace_packages.txt
raisin.page.egg-info/not-zip-safe
raisin.page.egg-info/requires.txt
raisin.page.egg-info/top_level.txt
raisin/page/__init__.py
raisin/page/pages.ini
raisin/page/templates/box.pt
raisin/page/templates/homepage.pt
raisin/page/templates/statistics.pt
raisin/page/templates/static/base.css
raisin/page/templates/static/favicon.ico
raisin/page/templates/static/images/buttonbg.gif
raisin/page/templates/static/images/favicon.ico
raisin/page/templates/static/images/footerbg.gif
raisin/page/templates/static/images/home.gif
raisin/page/templates/static/images/home_grad.gif
raisin/page/templates/static/images/logo-nocity.gif
raisin/page/templates/static/images/map_shorter.gif
raisin/page/templates/static/images/prevarrow.gif
raisin/page/templates/static/images/prevarrow_disabled.gif
raisin/page/templates/static/images/prevarrow_hover.gif
raisin/page/templates/static/images/splicing.gif
raisin/page/templates/static/images/splicing.png
raisin/page/templates/static/systemsbiology-visualizations/css/exportDataTable.css
raisin/page/templates/static/systemsbiology-visualizations/css/filterDataTableControl.css
raisin/page/templates/static/systemsbiology-visualizations/js/bioheatmap.js
raisin/page/templates/static/systemsbiology-visualizations/js/eventListenerAdapter.js
raisin/page/templates/static/systemsbiology-visualizations/js/exportDataTable.js
raisin/page/templates/static/systemsbiology-visualizations/js/filterDataTableControl.js
raisin/page/templates/static/systemsbiology-visualizations/js/load.js
raisin/page/templates/static/systemsbiology-visualizations/js/mappedSelectEventPropagation.js
raisin/page/templates/static/systemsbiology-visualizations/js/namespace.js
raisin/page/templates/static/systemsbiology-visualizations/js/visualizationDrawDataPropagation.js